{"bodyType":"prohibited","attrMax":0,"parseBody":false,"script":{"singletype":"optional","type":"single","rtexpr":true},"status":"implemeted","attrMin":0 ,"hasNameAppendix":false ,"name":"abort","type":"java","attributeCollection":true ,"attributeType":"fixed","nameSpaceSeperator":"","attributes":{"type":{"required":false ,"status":"implemeted","scriptSupport":"none","type":"string","description":"Either \"request\" (default) or \"page\". If \"request\", all request processing will be stopped. If \"page\", only processing in the current template will be stopped."},"showerror":{"required":false ,"status":"implemeted","scriptSupport":"optional","type":"string","description":"If supplied, a standard Lucee error page will be displayed showing the supplied error message."}},"description":"Stops processing of a request or template at the tag location.","nameSpace":"cf"}
